pz_rail_dnf-1.1.6.dist-info/licenses/LICENSE
rail/dnf/__init__.py
rail/dnf/_version.py
rail/estimation/algos/dnf.py
pz_rail_dnf-1.1.6.dist-info/METADATA
pz_rail_dnf-1.1.6.dist-info/WHEEL
pz_rail_dnf-1.1.6.dist-info/top_level.txt
pz_rail_dnf-1.1.6.dist-info/RECORD
